[{"id":1,"firstName":"Marc","lastName":"Scout","fonction":"Développeur","telephone":"0123456789","email":"marc.scout@email.fr","companyName":"Lumon Industries","date":"2024-03-31","coordonnees":{"idCoordonnees":1,"firstAddress":"2 rue de la poupée qui dort","secondAddress":"hey","codePostal":"57000","ville":"Metz","pays":"France"}},{"id":2,"firstName":"Harry","lastName":"Potter","fonction":"Sorcier","telephone":"0123456789","email":"harry.potter@email.fr","companyName":"Poudlard & Co.","date":"2024-06-03","coordonnees":{"idCoordonnees":2,"firstAddress":"Poudlard","secondAddress":"Ecole de magie","codePostal":"Poudlard","ville":"Chambre commune de Gryffondor","pays":"Pré-au-lard"}},{"id":3,"firstName":"Luc","lastName":"Skywalker","fonction":"Vendeur","telephone":"0123456789","email":"luc.kywalker@email.fr","companyName":"Ordre des Jedi","date":"2024-03-31","coordonnees":{"idCoordonnees":3,"firstAddress":"Dans les étoiles","secondAddress":"Star wars","codePostal":"Skywalker","ville":"Quelques part","pays":"USA"}}]